june/__init__.py
june/exc.py
june/logging.py
june/mpi_setup.py
june/paths.py
june/simulator.py
june/time.py
june/world.py
june/activity/__init__.py
june/activity/activity_manager.py
june/configs/config_example.yaml
june/configs/config_example_7.yaml
june/configs/config_stochastic.yaml
june/configs/logging.yaml
june/configs/defaults/rail_travel.yaml
june/configs/defaults/demography/ethnicity_encodings.yaml
june/configs/defaults/distributors/hospital_distributor.yaml
june/configs/defaults/distributors/household_distributor.yaml
june/configs/defaults/distributors/school_distributor.yaml
june/configs/defaults/distributors/worker_distributor.yaml
june/configs/defaults/epidemiology/infection/InfectionConstant.yaml
june/configs/defaults/epidemiology/infection/InfectionXNExp.yaml
june/configs/defaults/epidemiology/infection/symptoms/SymptomsConstant.yaml
june/configs/defaults/epidemiology/infection/symptoms/SymptomsGaussian.yaml
june/configs/defaults/epidemiology/infection/symptoms/SymptomsStep.yaml
june/configs/defaults/epidemiology/infection/symptoms/SymptomsTanh.yaml
june/configs/defaults/epidemiology/infection/symptoms/trajectories.yaml
june/configs/defaults/epidemiology/infection/transmission/TransmissionConstant.yaml
june/configs/defaults/epidemiology/infection/transmission/XNExp.yaml
june/configs/defaults/epidemiology/infection/transmission/b117.yaml
june/configs/defaults/epidemiology/infection/transmission/correction_nature.yaml
june/configs/defaults/epidemiology/infection/transmission/covid19.yaml
june/configs/defaults/epidemiology/infection/transmission/nature.yaml
june/configs/defaults/epidemiology/vaccines/vaccination_campaigns.yaml
june/configs/defaults/epidemiology/vaccines/vaccines.yaml
june/configs/defaults/event/events.yaml
june/configs/defaults/groups/care_home.yaml
june/configs/defaults/groups/companies.yaml
june/configs/defaults/groups/hospitals.yaml
june/configs/defaults/groups/households.yaml
june/configs/defaults/groups/schools.yaml
june-1.2.0.dist-info/LICENSE
june-1.2.0.dist-info/METADATA
june-1.2.0.dist-info/WHEEL
june-1.2.0.dist-info/top_level.txt
june-1.2.0.dist-info/RECORD
