Metadata-Version: 2.1
Name: june
Version: 1.2.0
Summary: A framework for high resolution Agent Based Modelling.
Home-page: https://github.com/idas-durham/june
Author: IDAS-Durham
Author-email: arnauq@protonmail.com
License: GPLv3 license
Platform: UNKNOWN
License-File: LICENSE
Requires-Dist: numpy (==1.21.5)
Requires-Dist: mpi4py (==3.1.3)
Requires-Dist: requests (==2.25.1)
Requires-Dist: pytest (==7.1.1)
Requires-Dist: pytest-cov (==3.0.0)
Requires-Dist: score-clustering (==0.1.4)
Requires-Dist: numba (==0.55.1)
Requires-Dist: tables (==3.7.0)
Requires-Dist: scipy (==1.8.0)
Requires-Dist: tqdm (==4.63.1)
Requires-Dist: h5py (==3.6.0)
Requires-Dist: pandas (==1.4.1)
Requires-Dist: recordclass (==0.17.2)
Requires-Dist: cufflinks (==0.17.3)
Requires-Dist: googlemaps (==4.4.5)
Requires-Dist: matplotlib (==3.5.1)
Requires-Dist: plotly (==4.14.3)
Requires-Dist: PyYAML (==6.0)
Requires-Dist: responses (==0.13.3)
Requires-Dist: scikit-learn (==1.0.2)
Requires-Dist: openpyxl (==3.0.9)
Requires-Dist: geopy (==2.2.0)
Requires-Dist: xlrd (==2.0.1)
